LICENSE
README.md
setup.py
odyssey_exchange_api/__init__.py
odyssey_exchange_api/base.py
odyssey_exchange_api.egg-info/PKG-INFO
odyssey_exchange_api.egg-info/SOURCES.txt
odyssey_exchange_api.egg-info/dependency_links.txt
odyssey_exchange_api.egg-info/requires.txt
odyssey_exchange_api.egg-info/top_level.txt
odyssey_exchange_api/clients/__init__.py
odyssey_exchange_api/clients/async_client.py
odyssey_exchange_api/clients/client.py
odyssey_exchange_api/clients/sync_client.py
odyssey_exchange_api/enums/__init__.py
odyssey_exchange_api/enums/futures/__init__.py
odyssey_exchange_api/enums/futures/contract_side.py
odyssey_exchange_api/enums/futures/contract_status.py
odyssey_exchange_api/enums/futures/contract_type.py
odyssey_exchange_api/enums/futures/order_side.py
odyssey_exchange_api/enums/futures/order_status.py
odyssey_exchange_api/enums/futures/order_type.py
odyssey_exchange_api/enums/futures/position_frozen_status.py
odyssey_exchange_api/enums/futures/position_model.py
odyssey_exchange_api/enums/futures/position_side.py
odyssey_exchange_api/enums/futures/position_status.py
odyssey_exchange_api/enums/futures/position_type.py
odyssey_exchange_api/enums/futures/time_in_force.py
odyssey_exchange_api/enums/futures/trigger_order_status.py
odyssey_exchange_api/enums/futures/trigger_type.py
odyssey_exchange_api/enums/spot/__init__.py
odyssey_exchange_api/enums/spot/order_side.py
odyssey_exchange_api/enums/spot/order_status.py
odyssey_exchange_api/enums/spot/order_type.py
odyssey_exchange_api/enums/websocket/__init__.py
odyssey_exchange_api/enums/websocket/event.py
odyssey_exchange_api/enums/websocket/order_side.py
odyssey_exchange_api/exceptions/__init__.py
odyssey_exchange_api/exceptions/base.py
odyssey_exchange_api/exceptions/general.py
odyssey_exchange_api/exceptions/other.py
odyssey_exchange_api/exceptions/rate_limit.py
odyssey_exchange_api/exceptions/request.py
odyssey_exchange_api/objects/__init__.py
odyssey_exchange_api/objects/futures/__init__.py
odyssey_exchange_api/objects/futures/account_coin_info.py
odyssey_exchange_api/objects/futures/account_position.py
odyssey_exchange_api/objects/futures/account_positions.py
odyssey_exchange_api/objects/futures/contract.py
