Metadata-Version: 2.1
Name: odyssey_exchange_api
Version: 0.0.5
Summary: Library for working with odyssey.trade
Home-page: https://github.com/Odyssey-Trade/python-odyssey-exchange-api
Author: goduni
License: MIT
Requires-Python: >=3.10
License-File: LICENSE
Requires-Dist: pydantic==2.9.2
Requires-Dist: httpx==0.27.2
Requires-Dist: websockets==13.1
